smpsave/__init__.py
smpsave/__main__.py
smpsave/cli/__init__.py
smpsave/cli/cli.py
smpsave/cli/log_config.py
smpsave/configuration/__init__.py
smpsave/configuration/baseconfig.py
smpsave/configuration/config_loader.py
smpsave/core/__init__.py
smpsave/core/config.py
smpsave/core/factory.py
smpsave/core/filesync.py
smpsave/core/sever_lifecycle.py
smpsave/discordbot/__init__.py
smpsave/discordbot/bot.py
smpsave/discordbot/config.py
smpsave/discordbot/factory.py
smpsave/provisioning/__init__.py
smpsave/provisioning/linode.py
smpsave/provisioning/provisioner.py
smpsave-0.2.1.dist-info/LICENSE
smpsave-0.2.1.dist-info/METADATA
smpsave-0.2.1.dist-info/WHEEL
smpsave-0.2.1.dist-info/entry_points.txt
smpsave-0.2.1.dist-info/top_level.txt
smpsave-0.2.1.dist-info/RECORD
