Metadata-Version: 2.1
Name: smpsave
Version: 0.2.1
Summary: Tool for provisioning private game servers on demand
Author-email: tbeeck <becktimd@gmail.com>
License: GNU GENERAL PUBLIC LICENSE
Project-URL: homepage, https://github.com/tbeeck/smpsave/
Project-URL: documentation, https://tbeeck.github.io/smpsave/
Classifier: License :: OSI Approved :: GNU General Public License v3 or later (GPLv3+)
Classifier: Development Status :: 2 - Pre-Alpha
Classifier: Intended Audience :: Developers
Classifier: Intended Audience :: System Administrators
Classifier: Topic :: Games/Entertainment
Classifier: Topic :: Utilities
Classifier: Programming Language :: Python :: 3.9
Classifier: Programming Language :: Python :: 3.10
Classifier: Programming Language :: Python :: 3.11
Classifier: Programming Language :: Python :: 3.12
Classifier: Programming Language :: Python :: 3.13
Requires-Python: >=3.9
License-File: LICENSE
Requires-Dist: discord.py >=2.3.2
Requires-Dist: linode-api4 >=5.12.1
Requires-Dist: click >=8.1.7
Requires-Dist: importlib-metadata ; python_version < "3.10"
